{"results": {"aflplusplus": {"libsndfile_7_1": {"sndfile_fuzzer": {"0": {"reached": {"SND007": 5}, "triggered": {"SND007": 15}}, "3": {"reached": {"SND007": 5}, "triggered": {"SND007": 15}}, "1": {"reached": {"SND007": 5}, "triggered": {"SND007": 15}}, "8": {"reached": {"SND007": 5}, "triggered": {"SND007": 15}}, "6": {"reached": {"SND007": 5}, "triggered": {"SND007": 15}}, "9": {"reached": {"SND007": 5}, "triggered": {"SND007": 15}}, "2": {"reached": {"SND007": 5}, "triggered": {"SND007": 15}}, "5": {"reached": {"SND007": 5}, "triggered": {"SND007": 15}}, "7": {"reached": {"SND007": 5}, "triggered": {"SND007": 15}}, "4": {"reached": {"SND007": 5}, "triggered": {"SND007": 15}}}}, "libpng_4_1": {"libpng_read_fuzzer": {"0": {"reached": {"PNG004": 5}}, "3": {"reached": {"PNG004": 5}}, "1": {"reached": {"PNG004": 5}}, "8": {"reached": {"PNG004": 5}}, "6": {"reached": {"PNG004": 5}}, "9": {"reached": {"PNG004": 5}}, "2": {"reached": {"PNG004": 5}}, "5": {"reached": {"PNG004": 5}}, "7": {"reached": {"PNG004": 5}}, "4": {"reached": {"PNG004": 5}}}}, "php_11_2": {"exif": {"0": {"reached": {"PHP011": 5}, "triggered": {"PHP011": 10}}, "3": {"reached": {"PHP011": 5}, "triggered": {"PHP011": 10}}, "1": {"reached": {"PHP011": 5}, "triggered": {"PHP011": 10}}, "8": {"reached": {"PHP011": 5}, "triggered": {"PHP011": 10}}, "6": {"reached": {"PHP011": 5}, "triggered": {"PHP011": 10}}, "9": {"reached": {"PHP011": 5}, "triggered": {"PHP011": 10}}, "2": {"reached": {"PHP011": 5}, "triggered": {"PHP011": 10}}, "5": {"reached": {"PHP011": 5}, "triggered": {"PHP011": 10}}, "7": {"reached": {"PHP011": 5}, "triggered": {"PHP011": 10}}, "4": {"reached": {"PHP011": 5}, "triggered": {"PHP011": 10}}}}, "poppler_9_1": {"pdf_fuzzer": {"0": {"reached": {"PDF009": 10}}, "3": {"reached": {"PDF009": 10}}, "1": {"reached": {"PDF009": 10}}, "8": {"reached": {"PDF009": 10}}, "6": {"reached": {"PDF009": 10}}, "9": {"reached": {"PDF009": 10}}, "2": {"reached": {"PDF009": 10}}, "5": {"reached": {"PDF009": 10}}, "7": {"reached": {"PDF009": 10}}, "4": {"reached": {"PDF009": 10}}}}, "openssl_1_5": {"client": {"0": {"reached": {"SSL001": 50}}, "3": {"reached": {"SSL001": 50}}, "1": {"reached": {"SSL001": 50}}, "8": {"reached": {"SSL001": 55}}, "6": {"reached": {"SSL001": 50}}, "9": {"reached": {"SSL001": 55}}, "2": {"reached": {"SSL001": 50}}, "5": {"reached": {"SSL001": 50}}, "7": {"reached": {"SSL001": 55}}, "4": {"reached": {"SSL001": 50}}}}, "libxml2_12_2": {"libxml2_xml_read_memory_fuzzer": {"0": {"reached": {"XML012": 5}}, "3": {"reached": {"XML012": 5}}, "1": {"reached": {"XML012": 5}}, "8": {"reached": {"XML012": 5}}, "6": {"reached": {"XML012": 5}}, "9": {"reached": {"XML012": 5}}, "2": {"reached": {"XML012": 5}}, "5": {"reached": {"XML012": 5}}, "7": {"reached": {"XML012": 5}}, "4": {"reached": {"XML012": 5}}}}, "libxml2_8_1": {"libxml2_xml_reader_for_file_fuzzer": {"0": {"reached": {"XML008": 10}}, "3": {"reached": {"XML008": 10}}, "1": {"reached": {"XML008": 10}}, "8": {"reached": {"XML008": 15}}, "6": {"reached": {"XML008": 10}}, "9": {"reached": {"XML008": 10}}, "2": {"reached": {"XML008": 10}}, "5": {"reached": {"XML008": 15}}, "7": {"reached": {"XML008": 10}}, "4": {"reached": {"XML008": 15}}}}, "libxml2_1_2": {"libxml2_xml_read_memory_fuzzer": {"0": {"reached": {"XML001": 5}, "triggered": {"XML001": 40}}, "3": {"reached": {"XML001": 5}, "triggered": {"XML001": 45}}, "1": {"reached": {"XML001": 5}, "triggered": {"XML001": 45}}, "8": {"reached": {"XML001": 5}, "triggered": {"XML001": 40}}, "6": {"reached": {"XML001": 5}, "triggered": {"XML001": 40}}, "9": {"reached": {"XML001": 5}, "triggered": {"XML001": 40}}, "2": {"reached": {"XML001": 5}, "triggered": {"XML001": 40}}, "5": {"reached": {"XML001": 5}, "triggered": {"XML001": 40}}, "7": {"reached": {"XML001": 5}, "triggered": {"XML001": 40}}, "4": {"reached": {"XML001": 5}, "triggered": {"XML001": 40}}}}, "libtiff_10_1": {"tiff_read_rgba_fuzzer": {"0": {"reached": {"TIF010": 5}}, "3": {"reached": {"TIF010": 5}}, "1": {"reached": {"TIF010": 5}}, "8": {"reached": {"TIF010": 5}}, "6": {"reached": {"TIF010": 5}}, "9": {"reached": {"TIF010": 5}}, "2": {"reached": {"TIF010": 5}}, "5": {"reached": {"TIF010": 5}}, "7": {"reached": {"TIF010": 5}}, "4": {"reached": {"TIF010": 5}}}}, "openssl_10_5": {"client": {"0": {"reached": {"SSL010": 5}}, "3": {"reached": {"SSL010": 5}}, "1": {"reached": {"SSL010": 5}}, "8": {"reached": {"SSL010": 5}}, "6": {"reached": {"SSL010": 5}}, "9": {"reached": {"SSL010": 5}}, "2": {"reached": {"SSL010": 5}}, "5": {"reached": {"SSL010": 5}}, "7": {"reached": {"SSL010": 5}}, "4": {"reached": {"SSL010": 5}}}}, "libtiff_7_1": {"tiff_read_rgba_fuzzer": {"0": {"reached": {"TIF007": 5}, "triggered": {"TIF007": 5}}, "3": {"reached": {"TIF007": 5}, "triggered": {"TIF007": 5}}, "1": {"reached": {"TIF007": 5}, "triggered": {"TIF007": 5}}, "8": {"reached": {"TIF007": 5}, "triggered": {"TIF007": 5}}, "6": {"reached": {"TIF007": 5}, "triggered": {"TIF007": 5}}, "9": {"reached": {"TIF007": 5}, "triggered": {"TIF007": 5}}, "2": {"reached": {"TIF007": 5}, "triggered": {"TIF007": 5}}, "5": {"reached": {"TIF007": 5}, "triggered": {"TIF007": 5}}, "7": {"reached": {"TIF007": 5}, "triggered": {"TIF007": 5}}, "4": {"reached": {"TIF007": 5}, "triggered": {"TIF007": 5}}}}, "sqlite3_18_1": {"sqlite3_fuzz": {"0": {"reached": {"SQL018": 5}, "triggered": {"SQL018": 5}}, "3": {"reached": {"SQL018": 5}, "triggered": {"SQL018": 5}}, "1": {"reached": {"SQL018": 5}, "triggered": {"SQL018": 5}}, "8": {"reached": {"SQL018": 5}, "triggered": {"SQL018": 5}}, "6": {"reached": {"SQL018": 5}, "triggered": {"SQL018": 5}}, "9": {"reached": {"SQL018": 5}, "triggered": {"SQL018": 5}}, "2": {"reached": {"SQL018": 5}, "triggered": {"SQL018": 5}}, "5": {"reached": {"SQL018": 5}, "triggered": {"SQL018": 5}}, "7": {"reached": {"SQL018": 5}, "triggered": {"SQL018": 5}}, "4": {"reached": {"SQL018": 5}, "triggered": {"SQL018": 5}}}}, "openssl_16_6": {"x509": {"0": {"reached": {"SSL016": 5}}, "3": {"reached": {"SSL016": 5}}, "1": {"reached": {"SSL016": 5}}, "8": {"reached": {"SSL016": 5}}, "6": {"reached": {"SSL016": 5}}, "9": {"reached": {"SSL016": 5}}, "2": {"reached": {"SSL016": 5}}, "5": {"reached": {"SSL016": 5}}, "7": {"reached": {"SSL016": 5}}, "4": {"reached": {"SSL016": 5}}}}, "openssl_20_4": {"server": {"0": {"reached": {"SSL020": 5}}, "3": {"reached": {"SSL020": 5}}, "1": {"reached": {"SSL020": 5}}, "8": {"reached": {"SSL020": 5}}, "6": {"reached": {"SSL020": 5}}, "9": {"reached": {"SSL020": 5}}, "2": {"reached": {"SSL020": 5}}, "5": {"reached": {"SSL020": 5}}, "7": {"reached": {"SSL020": 5}}, "4": {"reached": {"SSL020": 5}}}}}}}