{"results": {"windranger": {"libsndfile_7_1": {"sndfile_fuzzer": {"0": {"reached": {"SND007": 62.4}, "triggered": {"SND007": 92.4}}, "3": {"reached": {"SND007": 62.4}, "triggered": {"SND007": 92.4}}, "1": {"reached": {"SND007": 62.4}, "triggered": {"SND007": 92.4}}, "8": {"reached": {"SND007": 62.4}, "triggered": {"SND007": 92.4}}, "6": {"reached": {"SND007": 62.4}, "triggered": {"SND007": 92.4}}, "9": {"reached": {"SND007": 62.4}, "triggered": {"SND007": 92.4}}, "2": {"reached": {"SND007": 62.4}, "triggered": {"SND007": 92.4}}, "5": {"reached": {"SND007": 62.4}, "triggered": {"SND007": 92.4}}, "7": {"reached": {"SND007": 62.4}, "triggered": {"SND007": 92.4}}, "4": {"reached": {"SND007": 62.4}, "triggered": {"SND007": 92.4}}}}, "libpng_4_1": {"libpng_read_fuzzer": {"0": {"reached": {"PNG004": 16.9}}, "3": {"reached": {"PNG004": 16.9}}, "1": {"reached": {"PNG004": 16.9}}, "8": {"reached": {"PNG004": 16.9}}, "6": {"reached": {"PNG004": 16.9}}, "9": {"reached": {"PNG004": 16.9}}, "2": {"reached": {"PNG004": 16.9}}, "5": {"reached": {"PNG004": 16.9}}, "7": {"reached": {"PNG004": 16.9}}, "4": {"reached": {"PNG004": 16.9}}}}, "poppler_9_1": {"pdf_fuzzer": {"0": {"reached": {"PDF009": 99.0}}, "3": {"reached": {"PDF009": 99.0}}, "1": {"reached": {"PDF009": 99.0}}, "8": {"reached": {"PDF009": 99.0}}, "6": {"reached": {"PDF009": 99.0}}, "9": {"reached": {"PDF009": 99.0}}, "2": {"reached": {"PDF009": 99.0}}, "5": {"reached": {"PDF009": 99.0}}, "7": {"reached": {"PDF009": 99.0}}, "4": {"reached": {"PDF009": 99.0}}}}, "openssl_1_5": {"client": {"0": {"reached": {"SSL001": 111.6}}, "3": {"reached": {"SSL001": 111.6}}, "1": {"reached": {"SSL001": 111.6}}, "8": {"reached": {"SSL001": 111.6}}, "6": {"reached": {"SSL001": 111.6}}, "9": {"reached": {"SSL001": 111.6}}, "2": {"reached": {"SSL001": 111.6}}, "5": {"reached": {"SSL001": 111.6}}, "7": {"reached": {"SSL001": 111.6}}, "4": {"reached": {"SSL001": 111.6}}}}, "libxml2_12_2": {"libxml2_xml_read_memory_fuzzer": {"0": {"reached": {"XML012": 61.5}}, "3": {"reached": {"XML012": 61.5}}, "1": {"reached": {"XML012": 61.5}}, "8": {"reached": {"XML012": 61.5}}, "6": {"reached": {"XML012": 61.5}}, "9": {"reached": {"XML012": 61.5}}, "2": {"reached": {"XML012": 61.5}}, "5": {"reached": {"XML012": 61.5}}, "7": {"reached": {"XML012": 61.5}}, "4": {"reached": {"XML012": 61.5}}}}, "libxml2_8_1": {"libxml2_xml_reader_for_file_fuzzer": {"0": {"reached": {"XML008": 51.9}}, "3": {"reached": {"XML008": 51.9}}, "1": {"reached": {"XML008": 51.9}}, "8": {"reached": {"XML008": 51.9}}, "6": {"reached": {"XML008": 51.9}}, "9": {"reached": {"XML008": 51.9}}, "2": {"reached": {"XML008": 51.9}}, "5": {"reached": {"XML008": 51.9}}, "7": {"reached": {"XML008": 51.9}}, "4": {"reached": {"XML008": 51.9}}}}, "libxml2_1_2": {"libxml2_xml_read_memory_fuzzer": {"0": {"reached": {"XML001": 46.4}, "triggered": {"XML001": 56.4}}, "3": {"reached": {"XML001": 46.4}, "triggered": {"XML001": 56.4}}, "1": {"reached": {"XML001": 46.4}, "triggered": {"XML001": 56.4}}, "8": {"reached": {"XML001": 46.4}, "triggered": {"XML001": 56.4}}, "6": {"reached": {"XML001": 46.4}, "triggered": {"XML001": 56.4}}, "9": {"reached": {"XML001": 46.4}, "triggered": {"XML001": 56.4}}, "2": {"reached": {"XML001": 46.4}, "triggered": {"XML001": 56.4}}, "5": {"reached": {"XML001": 46.4}, "triggered": {"XML001": 56.4}}, "7": {"reached": {"XML001": 46.4}, "triggered": {"XML001": 56.4}}, "4": {"reached": {"XML001": 46.4}, "triggered": {"XML001": 56.4}}}}, "libtiff_10_1": {"tiff_read_rgba_fuzzer": {"0": {"reached": {"TIF010": 47.3}}, "3": {"reached": {"TIF010": 47.3}}, "1": {"reached": {"TIF010": 47.3}}, "8": {"reached": {"TIF010": 47.3}}, "6": {"reached": {"TIF010": 47.3}}, "9": {"reached": {"TIF010": 47.3}}, "2": {"reached": {"TIF010": 47.3}}, "5": {"reached": {"TIF010": 47.3}}, "7": {"reached": {"TIF010": 47.3}}, "4": {"reached": {"TIF010": 47.3}}}}, "openssl_10_5": {"client": {"0": {"reached": {"SSL010": 129.0}}, "3": {"reached": {"SSL010": 129.0}}, "1": {"reached": {"SSL010": 129.0}}, "8": {"reached": {"SSL010": 129.0}}, "6": {"reached": {"SSL010": 129.0}}, "9": {"reached": {"SSL010": 129.0}}, "2": {"reached": {"SSL010": 129.0}}, "5": {"reached": {"SSL010": 129.0}}, "7": {"reached": {"SSL010": 129.0}}, "4": {"reached": {"SSL010": 129.0}}}}, "libtiff_7_1": {"tiff_read_rgba_fuzzer": {"0": {"reached": {"TIF007": 41.9}, "triggered": {"TIF007": 46.9}}, "3": {"reached": {"TIF007": 41.9}, "triggered": {"TIF007": 46.9}}, "1": {"reached": {"TIF007": 41.9}, "triggered": {"TIF007": 46.9}}, "8": {"reached": {"TIF007": 41.9}, "triggered": {"TIF007": 46.9}}, "6": {"reached": {"TIF007": 41.9}, "triggered": {"TIF007": 46.9}}, "9": {"reached": {"TIF007": 41.9}, "triggered": {"TIF007": 46.9}}, "2": {"reached": {"TIF007": 41.9}, "triggered": {"TIF007": 46.9}}, "5": {"reached": {"TIF007": 41.9}, "triggered": {"TIF007": 46.9}}, "7": {"reached": {"TIF007": 41.9}, "triggered": {"TIF007": 46.9}}, "4": {"reached": {"TIF007": 41.9}, "triggered": {"TIF007": 46.9}}}}, "sqlite3_20_1": {"sqlite3_fuzz": {"4": {"reached": {"SQL020": 560.3}, "triggered": {"SQL020": 560.3}}}}, "sqlite3_18_1": {"sqlite3_fuzz": {"0": {"reached": {"SQL018": 56.9}, "triggered": {"SQL018": 61.9}}, "3": {"reached": {"SQL018": 56.9}, "triggered": {"SQL018": 61.9}}, "1": {"reached": {"SQL018": 56.9}, "triggered": {"SQL018": 61.9}}, "8": {"reached": {"SQL018": 56.9}, "triggered": {"SQL018": 61.9}}, "6": {"reached": {"SQL018": 56.9}, "triggered": {"SQL018": 61.9}}, "9": {"reached": {"SQL018": 56.9}, "triggered": {"SQL018": 61.9}}, "2": {"reached": {"SQL018": 56.9}, "triggered": {"SQL018": 61.9}}, "5": {"reached": {"SQL018": 56.9}, "triggered": {"SQL018": 61.9}}, "7": {"reached": {"SQL018": 56.9}, "triggered": {"SQL018": 61.9}}, "4": {"reached": {"SQL018": 56.9}, "triggered": {"SQL018": 61.9}}}}, "openssl_16_6": {"x509": {"0": {"reached": {"SSL016": 63.4}}, "3": {"reached": {"SSL016": 63.4}}, "1": {"reached": {"SSL016": 63.4}}, "8": {"reached": {"SSL016": 63.4}}, "6": {"reached": {"SSL016": 63.4}}, "9": {"reached": {"SSL016": 63.4}}, "2": {"reached": {"SSL016": 63.4}}, "5": {"reached": {"SSL016": 63.4}}, "7": {"reached": {"SSL016": 63.4}}, "4": {"reached": {"SSL016": 63.4}}}}, "openssl_20_4": {"server": {"0": {"reached": {"SSL020": 59.4}}, "3": {"reached": {"SSL020": 59.4}}, "1": {"reached": {"SSL020": 59.4}}, "8": {"reached": {"SSL020": 59.4}}, "6": {"reached": {"SSL020": 59.4}}, "9": {"reached": {"SSL020": 59.4}}, "2": {"reached": {"SSL020": 59.4}}, "5": {"reached": {"SSL020": 59.4}}, "7": {"reached": {"SSL020": 59.4}}, "4": {"reached": {"SSL020": 59.4}}}}}}}